ValManager/__init__.py
ValManager/config.py
ValManager/loadout.py
ValManager/storage.py
ValManager/structs.py
ValManager/backup/__init__.py
ValManager/backup/backup.py
ValManager/backup/storage.py
ValManager/backup/transform.py
ValManager-0.0.1.dist-info/LICENSE
ValManager-0.0.1.dist-info/METADATA
ValManager-0.0.1.dist-info/WHEEL
ValManager-0.0.1.dist-info/top_level.txt
ValManager-0.0.1.dist-info/RECORD
