Metadata-Version: 2.1
Name: ValManager
Version: 0.0.1
Author: PWall
License: GPL-3.0
Project-URL: Homepage, https://github.com/ValUtils/ValManager
Requires-Python: >=3.8
License-File: LICENSE
Requires-Dist: ValVault
Requires-Dist: ValLib
Requires-Dist: ValStorage
Requires-Dist: dataclasses-json
Requires-Dist: pick
